Workbook

Sheet Resumo
A1: RESUMO FINANCEIRO — ROBLE FUERTE
A2: Atualizado automaticamente — abra o arquivo para recalcular
A4: Total a Receber (Pendente) | C4: Total a Pagar (Pendente) | E4: Saldo Projetado
A5: =SUMIFS(Contas_a_Receber!F5:F205,Contas_a_Receber!H5:H205,"Pendente") -> 42400 | C5: =SUMIFS(Contas_a_Pagar!F5:F205,Contas_a_Pagar!I5:I205,"Pendente") -> 7955 | E5: =B5-D5 -> 0
A8: Faturas VENCIDAS (€) | C8: Pagamentos VENCIDOS (€) | E8: Custos Fixos Mensais
A9: =SUMPRODUCT((Contas_a_Receber!H5:H205="Pendente")*(Contas_a_Receber!G5:G205<TODAY())*(Contas_a_Receber!G5:G205<>"")*Contas_a_Receber!F5:F205) -> 0 | C9: =SUMPRODUCT((Contas_a_Pagar!I5:I205="Pendente")*(Contas_a_Pagar!H5:H205<TODAY())*(Contas_a_Pagar!H5:H205<>"")*Contas_a_Pagar!F5:F205) -> 0 | E9: =SUM(Custos_Fixos!D5:D50) -> 59360
A12: Impostos Pendentes (€) | C12: Nº Faturas a Receber | E12: Nº Contas a Pagar
A13: =SUMIFS(Impostos!D5:D35,Impostos!F5:F35,"Pendente") -> 0 | C13: =COUNTIF(Contas_a_Receber!H5:H205,"Pendente") -> 3 | E13: =COUNTIF(Contas_a_Pagar!I5:I205,"Pendente") -> 6
A16: SEMÁFORO GERAL DA EMPRESA
A17: Liquidez: | B17: =IF(E5>0,"🟢 SAUDÁVEL — Recebíveis cobrem pagamentos","🔴 ATENÇÃO — Pagamentos pendentes superam recebimentos") -> 🔴 ATENÇÃO — Pagamentos pendentes superam recebimentos
A18: Vencidos: | B18: =IF(AND(B9=0,D9=0),"🟢 OK — Sem vencidos",IF(B9>D9,"🟡 Há faturas vencidas a cobrar","🔴 URGENTE — Pagamentos vencidos")) -> 🟢 OK — Sem vencidos
A19: Impostos: | B19: =IF(A13=0,"🟢 Em dia","🟡 Há impostos pendentes — verificar calendário") -> 🟢 Em dia
A22: COMO USAR ESTA PLANILHA
A23: 1. Lance contas a pagar e receber nas abas correspondentes assim que chegarem as faturas.
A24: 2. O semáforo é AUTOMÁTICO: 🔴 vencida, 🟡 vence em até 7 dias, 🟢 ok ou pago.
A25: 3. Atualize o "Status" para "Pago" + data de pagamento — o item sai do total pendente sozinho.
A26: 4. Os Custos Fixos rodam todo mês — replique no Contas a Pagar a cada virada de mês.
A27: 5. O Fluxo de Caixa serve para PROJETAR — preencha estimativas e veja o saldo acumulado.
A28: 6. Impostos: confira mensalmente o calendário fiscal junto à Gestoria.

Sheet Contas_a_Pagar
A1: CONTAS A PAGAR
A2: Fornecedores, funcionários, impostos, custos fixos — com semáforo automático
E3: Total Pendente: | F3: =SUMIFS(F5:F205,I5:I205,"Pendente") -> 7955
A4: Data Lanç. | B4: Fornecedor/Categoria | C4: Tipo | D4: Descrição | E4: Nº Fatura | F4: Valor (€) | G4: Emissão | H4: Vencimento | I4: Status | J4: Data Pagto | K4: Semáforo | L4: Dias p/ Vencer
A5: 2026-05-01 | B5: Maderas Madrid S.L. | C5: Fornecedor | D5: MDF + contraplacado pedido #1245 | E5: F2026-145 | F5: 1450 | G5: 2026-05-01 | H5: 2026-05-31 | I5: Pendente | K5: =IF(I5="Pago","✓ OK",IF(H5="","",IF(H5<TODAY(),"🔴 VENCIDA",IF(H5-TODAY()<=7,"🟡 ATENÇÃO","🟢 OK")))) -> 🟢 OK | L5: =IF(H5="","",H5-TODAY()) -> 16
A6: 2026-05-03 | B6: Lacas Premium | C6: Fornecedor | D6: Laca poliuretano branca 50L | E6: F2026-077 | F6: 945 | G6: 2026-05-03 | H6: 2026-05-03 | I6: Pago | J6: 2026-05-03 | K6: =IF(I6="Pago","✓ OK",IF(H6="","",IF(H6<TODAY(),"🔴 VENCIDA",IF(H6-TODAY()<=7,"🟡 ATENÇÃO","🟢 OK")))) -> ✓ OK | L6: =IF(H6="","",H6-TODAY()) -> -12
A7: 2026-05-05 | B7: Aluguel Nave Industrial | C7: Custo Fixo | D7: Aluguel mensal nave | E7: REC-05 | F7: 2200 | G7: 2026-05-01 | H7: 2026-05-05 | I7: Pago | J7: 2026-05-05 | K7: =IF(I7="Pago","✓ OK",IF(H7="","",IF(H7<TODAY(),"🔴 VENCIDA",IF(H7-TODAY()<=7,"🟡 ATENÇÃO","🟢 OK")))) -> ✓ OK | L7: =IF(H7="","",H7-TODAY()) -> -10
A8: 2026-05-10 | B8: Iberdrola | C8: Custo Fixo | D8: Luz fábrica + escritório | E8: IB-05-26 | F8: 480 | G8: 2026-05-10 | H8: 2026-05-20 | I8: Pendente | K8: =IF(I8="Pago","✓ OK",IF(H8="","",IF(H8<TODAY(),"🔴 VENCIDA",IF(H8-TODAY()<=7,"🟡 ATENÇÃO","🟢 OK")))) -> 🟡 ATENÇÃO | L8: =IF(H8="","",H8-TODAY()) -> 5
A9: 2026-05-12 | B9: Canal Isabel II | C9: Custo Fixo | D9: Água | E9: CAN-05 | F9: 95 | G9: 2026-05-12 | H9: 2026-05-25 | I9: Pendente | K9: =IF(I9="Pago","✓ OK",IF(H9="","",IF(H9<TODAY(),"🔴 VENCIDA",IF(H9-TODAY()<=7,"🟡 ATENÇÃO","🟢 OK")))) -> 🟢 OK | L9: =IF(H9="","",H9-TODAY()) -> 10
A10: 2026-05-15 | B10: Gestoria Fiscal | C10: Custo Fixo | D10: Serviços contabilidade maio | E10: G-05-26 | F10: 350 | G10: 2026-05-15 | H10: 2026-05-30 | I10: Pendente | K10: =IF(I10="Pago","✓ OK",IF(H10="","",IF(H10<TODAY(),"🔴 VENCIDA",IF(H10-TODAY()<=7,"🟡 ATENÇÃO","🟢 OK")))) -> 🟢 OK | L10: =IF(H10="","",H10-TODAY()) -> 15
A11: 2026-05-15 | B11: Funcionários — Fábrica | C11: Folha Pagto | D11: Salários maio fábrica | E11: NOM-05A | F11: 5400 | G11: 2026-05-15 | H11: 2026-05-30 | I11: Pendente | K11: =IF(I11="Pago","✓ OK",IF(H11="","",IF(H11<TODAY(),"🔴 VENCIDA",IF(H11-TODAY()<=7,"🟡 ATENÇÃO","🟢 OK")))) -> 🟢 OK | L11: =IF(H11="","",H11-TODAY()) -> 15
A12: 2026-05-20 | B12: Hacienda — IVA Q1 | C12: Imposto | D12: IVA 1º trimestre (modelo 303) | E12: M303-Q1 | F12: 3850 | G12: 2026-04-01 | H12: 2026-04-20 | I12: Pago | J12: 2026-04-19 | K12: =IF(I12="Pago","✓ OK",IF(H12="","",IF(H12<TODAY(),"🔴 VENCIDA",IF(H12-TODAY()<=7,"🟡 ATENÇÃO","🟢 OK")))) -> ✓ OK | L12: =IF(H12="","",H12-TODAY()) -> -25
A13: 2026-05-22 | B13: Combustível Furgões | C13: Custo Variável | D13: Diesel maio | E13: CEPSA-05 | F13: 280 | G13: 2026-05-22 | H13: 2026-05-22 | I13: Pago | J13: 2026-05-22 | K13: =IF(I13="Pago","✓ OK",IF(H13="","",IF(H13<TODAY(),"🔴 VENCIDA",IF(H13-TODAY()<=7,"🟡 ATENÇÃO","🟢 OK")))) -> ✓ OK | L13: =IF(H13="","",H13-TODAY()) -> 7
A14: 2026-05-25 | B14: Seguro Responsabilidade Civil | C14: Custo Fixo | D14: Mensalidade seguro | E14: SEG-05 | F14: 180 | G14: 2026-05-25 | H14: 2026-06-05 | I14: Pendente | K14: =IF(I14="Pago","✓ OK",IF(H14="","",IF(H14<TODAY(),"🔴 VENCIDA",IF(H14-TODAY()<=7,"🟡 ATENÇÃO","🟢 OK")))) -> 🟢 OK | L14: =IF(H14="","",H14-TODAY()) -> 21
K15: =IF(I15="Pago","✓ OK",IF(H15="","",IF(H15<TODAY(),"🔴 VENCIDA",IF(H15-TODAY()<=7,"🟡 ATENÇÃO","🟢 OK")))) | L15: =IF(H15="","",H15-TODAY())
K16: =IF(I16="Pago","✓ OK",IF(H16="","",IF(H16<TODAY(),"🔴 VENCIDA",IF(H16-TODAY()<=7,"🟡 ATENÇÃO","🟢 OK")))) | L16: =IF(H16="","",H16-TODAY())
K17: =IF(I17="Pago","✓ OK",IF(H17="","",IF(H17<TODAY(),"🔴 VENCIDA",IF(H17-TODAY()<=7,"🟡 ATENÇÃO","🟢 OK")))) | L17: =IF(H17="","",H17-TODAY())
K18: =IF(I18="Pago","✓ OK",IF(H18="","",IF(H18<TODAY(),"🔴 VENCIDA",IF(H18-TODAY()<=7,"🟡 ATENÇÃO","🟢 OK")))) | L18: =IF(H18="","",H18-TODAY())
K19: =IF(I19="Pago","✓ OK",IF(H19="","",IF(H19<TODAY(),"🔴 VENCIDA",IF(H19-TODAY()<=7,"🟡 ATENÇÃO","🟢 OK")))) | L19: =IF(H19="","",H19-TODAY())
K20: =IF(I20="Pago","✓ OK",IF(H20="","",IF(H20<TODAY(),"🔴 VENCIDA",IF(H20-TODAY()<=7,"🟡 ATENÇÃO","🟢 OK")))) | L20: =IF(H20="","",H20-TODAY())
K21: =IF(I21="Pago","✓ OK",IF(H21="","",IF(H21<TODAY(),"🔴 VENCIDA",IF(H21-TODAY()<=7,"🟡 ATENÇÃO","🟢 OK")))) | L21: =IF(H21="","",H21-TODAY())
K22: =IF(I22="Pago","✓ OK",IF(H22="","",IF(H22<TODAY(),"🔴 VENCIDA",IF(H22-TODAY()<=7,"🟡 ATENÇÃO","🟢 OK")))) | L22: =IF(H22="","",H22-TODAY())
K23: =IF(I23="Pago","✓ OK",IF(H23="","",IF(H23<TODAY(),"🔴 VENCIDA",IF(H23-TODAY()<=7,"🟡 ATENÇÃO","🟢 OK")))) | L23: =IF(H23="","",H23-TODAY())
K24: =IF(I24="Pago","✓ OK",IF(H24="","",IF(H24<TODAY(),"🔴 VENCIDA",IF(H24-TODAY()<=7,"🟡 ATENÇÃO","🟢 OK")))) | L24: =IF(H24="","",H24-TODAY())
K25: =IF(I25="Pago","✓ OK",IF(H25="","",IF(H25<TODAY(),"🔴 VENCIDA",IF(H25-TODAY()<=7,"🟡 ATENÇÃO","🟢 OK")))) | L25: =IF(H25="","",H25-TODAY())
K26: =IF(I26="Pago","✓ OK",IF(H26="","",IF(H26<TODAY(),"🔴 VENCIDA",IF(H26-TODAY()<=7,"🟡 ATENÇÃO","🟢 OK")))) | L26: =IF(H26="","",H26-TODAY())
... K204: =IF(I204="Pago","✓ OK",IF(H204="","",IF(H204<TODAY(),"🔴 VENCIDA",IF(H204-TODAY()<=7,"🟡 ATENÇÃO","🟢 OK")))) | L204: =IF(H204="","",H204-TODAY())

Sheet Contas_a_Receber
A1: CONTAS A RECEBER
A2: Faturas emitidas para clientes, arquitetos, reformistas e empresas
E3: Total a Receber: | F3: =SUMIFS(F5:F205,H5:H205,"Pendente") -> 42400
A4: Data Emissão | B4: Cliente | C4: Projeto | D4: Tipo | E4: Nº Fatura | F4: Valor (€) | G4: Vencimento | H4: Status | I4: Data Recebto | J4: Forma Pagto | K4: Semáforo | L4: Dias p/ Vencer
A5: 2026-04-15 | B5: Maria García | C5: Cozinha + armários Serrano | D5: Cliente Final | E5: F2026-001 | F5: 8500 | G5: 2026-05-15 | H5: Pendente | J5: Transferência | K5: =IF(H5="Pago","✓ OK",IF(G5="","",IF(G5<TODAY(),"🔴 VENCIDA",IF(G5-TODAY()<=7,"🟡 ATENÇÃO","🟢 OK")))) -> 🟡 ATENÇÃO | L5: =IF(G5="","",G5-TODAY()) -> 0
A6: 2026-04-20 | B6: Estudio ABC | C6: Obra Goya 12 — portas lacadas | D6: Arquiteto | E6: F2026-002 | F6: 12400 | G6: 2026-05-20 | H6: Pendente | J6: Transferência | K6: =IF(H6="Pago","✓ OK",IF(G6="","",IF(G6<TODAY(),"🔴 VENCIDA",IF(G6-TODAY()<=7,"🟡 ATENÇÃO","🟢 OK")))) -> 🟡 ATENÇÃO | L6: =IF(G6="","",G6-TODAY()) -> 5
A7: 2026-03-10 | B7: Reformas López | C7: Pack 12 portas enrasadas | D7: Reformista | E7: F2026-003 | F7: 6800 | G7: 2026-04-10 | H7: Pago | I7: 2026-04-08 | J7: Transferência | K7: =IF(H7="Pago","✓ OK",IF(G7="","",IF(G7<TODAY(),"🔴 VENCIDA",IF(G7-TODAY()<=7,"🟡 ATENÇÃO","🟢 OK")))) -> ✓ OK | L7: =IF(G7="","",G7-TODAY()) -> -35
A8: 2026-04-25 | B8: Construtora Núñez | C8: Armários edifício Chamberí (3 unid.) | D8: Construtora | E8: F2026-004 | F8: 21500 | G8: 2026-05-25 | H8: Pendente | J8: Transferência | K8: =IF(H8="Pago","✓ OK",IF(G8="","",IF(G8<TODAY(),"🔴 VENCIDA",IF(G8-TODAY()<=7,"🟡 ATENÇÃO","🟢 OK")))) -> 🟢 OK | L8: =IF(G8="","",G8-TODAY()) -> 10
A9: 2026-05-02 | B9: Pedro Martínez | C9: Porta corredera + armário | D9: Cliente Final | E9: F2026-005 | F9: 3200 | G9: 2026-05-15 | H9: Pago | I9: 2026-05-14 | J9: Transferência | K9: =IF(H9="Pago","✓ OK",IF(G9="","",IF(G9<TODAY(),"🔴 VENCIDA",IF(G9-TODAY()<=7,"🟡 ATENÇÃO","🟢 OK")))) -> ✓ OK | L9: =IF(G9="","",G9-TODAY()) -> 0
K10: =IF(H10="Pago","✓ OK",IF(G10="","",IF(G10<TODAY(),"🔴 VENCIDA",IF(G10-TODAY()<=7,"🟡 ATENÇÃO","🟢 OK")))) | L10: =IF(G10="","",G10-TODAY())
K11: =IF(H11="Pago","✓ OK",IF(G11="","",IF(G11<TODAY(),"🔴 VENCIDA",IF(G11-TODAY()<=7,"🟡 ATENÇÃO","🟢 OK")))) | L11: =IF(G11="","",G11-TODAY())
K12: =IF(H12="Pago","✓ OK",IF(G12="","",IF(G12<TODAY(),"🔴 VENCIDA",IF(G12-TODAY()<=7,"🟡 ATENÇÃO","🟢 OK")))) | L12: =IF(G12="","",G12-TODAY())
K13: =IF(H13="Pago","✓ OK",IF(G13="","",IF(G13<TODAY(),"🔴 VENCIDA",IF(G13-TODAY()<=7,"🟡 ATENÇÃO","🟢 OK")))) | L13: =IF(G13="","",G13-TODAY())
K14: =IF(H14="Pago","✓ OK",IF(G14="","",IF(G14<TODAY(),"🔴 VENCIDA",IF(G14-TODAY()<=7,"🟡 ATENÇÃO","🟢 OK")))) | L14: =IF(G14="","",G14-TODAY())
K15: =IF(H15="Pago","✓ OK",IF(G15="","",IF(G15<TODAY(),"🔴 VENCIDA",IF(G15-TODAY()<=7,"🟡 ATENÇÃO","🟢 OK")))) | L15: =IF(G15="","",G15-TODAY())
K16: =IF(H16="Pago","✓ OK",IF(G16="","",IF(G16<TODAY(),"🔴 VENCIDA",IF(G16-TODAY()<=7,"🟡 ATENÇÃO","🟢 OK")))) | L16: =IF(G16="","",G16-TODAY())
K17: =IF(H17="Pago","✓ OK",IF(G17="","",IF(G17<TODAY(),"🔴 VENCIDA",IF(G17-TODAY()<=7,"🟡 ATENÇÃO","🟢 OK")))) | L17: =IF(G17="","",G17-TODAY())
K18: =IF(H18="Pago","✓ OK",IF(G18="","",IF(G18<TODAY(),"🔴 VENCIDA",IF(G18-TODAY()<=7,"🟡 ATENÇÃO","🟢 OK")))) | L18: =IF(G18="","",G18-TODAY())
K19: =IF(H19="Pago","✓ OK",IF(G19="","",IF(G19<TODAY(),"🔴 VENCIDA",IF(G19-TODAY()<=7,"🟡 ATENÇÃO","🟢 OK")))) | L19: =IF(G19="","",G19-TODAY())
K20: =IF(H20="Pago","✓ OK",IF(G20="","",IF(G20<TODAY(),"🔴 VENCIDA",IF(G20-TODAY()<=7,"🟡 ATENÇÃO","🟢 OK")))) | L20: =IF(G20="","",G20-TODAY())
K21: =IF(H21="Pago","✓ OK",IF(G21="","",IF(G21<TODAY(),"🔴 VENCIDA",IF(G21-TODAY()<=7,"🟡 ATENÇÃO","🟢 OK")))) | L21: =IF(G21="","",G21-TODAY())
... K204: =IF(H204="Pago","✓ OK",IF(G204="","",IF(G204<TODAY(),"🔴 VENCIDA",IF(G204-TODAY()<=7,"🟡 ATENÇÃO","🟢 OK")))) | L204: =IF(G204="","",G204-TODAY())

Sheet Custos_Fixos
A1: CUSTOS FIXOS MENSAIS
A2: Tudo que sai todos os meses, independente do volume de vendas
A4: Categoria | B4: Descrição | C4: Fornecedor | D4: Valor Mensal (€) | E4: Dia Vencimento | F4: Forma Pagto | G4: Observações
A5: Aluguel | B5: Nave industrial + escritório | C5: Imobiliária X | D5: 2200 | E5: 5 | F5: Transferência | G5: Reajuste anual jan.
A6: Luz | B6: Iberdrola — fábrica | C6: Iberdrola | D6: 480 | E6: 20 | F6: Débito automático | G6: Aumenta no inverno
A7: Água | B7: Canal Isabel II | C7: Canal Isabel II | D7: 95 | E7: 25 | F7: Débito automático
A8: Internet/Telefone | B8: Movistar fibra | C8: Movistar | D8: 75 | E8: 10 | F8: Débito automático
A9: Gestoria | B9: Contabilidade e fiscal | C9: Gestoria X | D9: 350 | E9: 30 | F9: Transferência
A10: Seguros | B10: RC + multirriscos nave | C10: Mapfre | D10: 180 | E10: 5 | F10: Débito automático
A11: Combustível | B11: Furgões de instalação | C11: CEPSA | D11: 350 | E11: 30 | F11: Cartão empresa | G11: Média mensal
A12: Software/Cloud | B12: Notion, Google, etc. | C12: Vários | D12: 60 | E12: 1 | F12: Cartão
A13: Manutenção CNC | B13: Lâminas, brocas, manutenção | C13: Vários | D13: 200 | E13: 30 | F13: Vários | G13: Média
A14: Limpeza | B14: Limpeza nave | C14: Servicios L. | D14: 250 | E14: 30 | F14: Transferência
C16: TOTAL MENSAL: | D16: =SUM(D5:D14) -> 4240
C17: TOTAL ANUAL: | D17: =D16*12 -> 50880

Sheet Impostos
A1: IMPOSTOS — Calendário Fiscal
A2: IVA trimestral, IRPF, IS, recolhimentos — Espanha
A4: Tipo | B4: Modelo | C4: Período | D4: Valor (€) | E4: Vencimento | F4: Status | G4: Data Pagto | H4: Semáforo | I4: Observações
A5: IVA Trimestral | B5: 303 | C5: 1º Trim 2026 | D5: 3850 | E5: 2026-04-20 | F5: Pago | G5: 2026-04-19 | H5: =IF(F5="Pago","✓ OK",IF(E5="","",IF(E5<TODAY(),"🔴 VENCIDO",IF(E5-TODAY()<=15,"🟡 ATENÇÃO","🟢 OK")))) -> ✓ OK
A6: IRPF Retenções | B6: 111 | C6: 1º Trim 2026 | D6: 980 | E6: 2026-04-20 | F6: Pago | G6: 2026-04-19 | H6: =IF(F6="Pago","✓ OK",IF(E6="","",IF(E6<TODAY(),"🔴 VENCIDO",IF(E6-TODAY()<=15,"🟡 ATENÇÃO","🟢 OK")))) -> ✓ OK
A7: Pagto Frac. IRPF | B7: 130 | C7: 1º Trim 2026 | D7: 1200 | E7: 2026-04-20 | F7: Pago | G7: 2026-04-19 | H7: =IF(F7="Pago","✓ OK",IF(E7="","",IF(E7<TODAY(),"🔴 VENCIDO",IF(E7-TODAY()<=15,"🟡 ATENÇÃO","🟢 OK")))) -> ✓ OK
A8: IVA Trimestral | B8: 303 | C8: 2º Trim 2026 | E8: 2026-07-20 | F8: Pendente | H8: =IF(F8="Pago","✓ OK",IF(E8="","",IF(E8<TODAY(),"🔴 VENCIDO",IF(E8-TODAY()<=15,"🟡 ATENÇÃO","🟢 OK")))) -> 🟢 OK
A9: IRPF Retenções | B9: 111 | C9: 2º Trim 2026 | E9: 2026-07-20 | F9: Pendente | H9: =IF(F9="Pago","✓ OK",IF(E9="","",IF(E9<TODAY(),"🔴 VENCIDO",IF(E9-TODAY()<=15,"🟡 ATENÇÃO","🟢 OK")))) -> 🟢 OK
A10: Pagto Frac. IRPF | B10: 130 | C10: 2º Trim 2026 | E10: 2026-07-20 | F10: Pendente | H10: =IF(F10="Pago","✓ OK",IF(E10="","",IF(E10<TODAY(),"🔴 VENCIDO",IF(E10-TODAY()<=15,"🟡 ATENÇÃO","🟢 OK")))) -> 🟢 OK
A11: Resumo Anual IVA | B11: 390 | C11: 2025 | E11: 2026-01-30 | F11: Pago | G11: 2026-01-28 | H11: =IF(F11="Pago","✓ OK",IF(E11="","",IF(E11<TODAY(),"🔴 VENCIDO",IF(E11-TODAY()<=15,"🟡 ATENÇÃO","🟢 OK")))) -> ✓ OK
A12: Resumo Operações | B12: 347 | C12: 2025 | E12: 2026-02-28 | F12: Pago | G12: 2026-02-25 | H12: =IF(F12="Pago","✓ OK",IF(E12="","",IF(E12<TODAY(),"🔴 VENCIDO",IF(E12-TODAY()<=15,"🟡 ATENÇÃO","🟢 OK")))) -> ✓ OK
H13: =IF(F13="Pago","✓ OK",IF(E13="","",IF(E13<TODAY(),"🔴 VENCIDO",IF(E13-TODAY()<=15,"🟡 ATENÇÃO","🟢 OK"))))
H14: =IF(F14="Pago","✓ OK",IF(E14="","",IF(E14<TODAY(),"🔴 VENCIDO",IF(E14-TODAY()<=15,"🟡 ATENÇÃO","🟢 OK"))))
H15: =IF(F15="Pago","✓ OK",IF(E15="","",IF(E15<TODAY(),"🔴 VENCIDO",IF(E15-TODAY()<=15,"🟡 ATENÇÃO","🟢 OK"))))
H16: =IF(F16="Pago","✓ OK",IF(E16="","",IF(E16<TODAY(),"🔴 VENCIDO",IF(E16-TODAY()<=15,"🟡 ATENÇÃO","🟢 OK"))))
H17: =IF(F17="Pago","✓ OK",IF(E17="","",IF(E17<TODAY(),"🔴 VENCIDO",IF(E17-TODAY()<=15,"🟡 ATENÇÃO","🟢 OK"))))
H18: =IF(F18="Pago","✓ OK",IF(E18="","",IF(E18<TODAY(),"🔴 VENCIDO",IF(E18-TODAY()<=15,"🟡 ATENÇÃO","🟢 OK"))))
H19: =IF(F19="Pago","✓ OK",IF(E19="","",IF(E19<TODAY(),"🔴 VENCIDO",IF(E19-TODAY()<=15,"🟡 ATENÇÃO","🟢 OK"))))
H20: =IF(F20="Pago","✓ OK",IF(E20="","",IF(E20<TODAY(),"🔴 VENCIDO",IF(E20-TODAY()<=15,"🟡 ATENÇÃO","🟢 OK"))))
H21: =IF(F21="Pago","✓ OK",IF(E21="","",IF(E21<TODAY(),"🔴 VENCIDO",IF(E21-TODAY()<=15,"🟡 ATENÇÃO","🟢 OK"))))
H22: =IF(F22="Pago","✓ OK",IF(E22="","",IF(E22<TODAY(),"🔴 VENCIDO",IF(E22-TODAY()<=15,"🟡 ATENÇÃO","🟢 OK"))))
H23: =IF(F23="Pago","✓ OK",IF(E23="","",IF(E23<TODAY(),"🔴 VENCIDO",IF(E23-TODAY()<=15,"🟡 ATENÇÃO","🟢 OK"))))
H24: =IF(F24="Pago","✓ OK",IF(E24="","",IF(E24<TODAY(),"🔴 VENCIDO",IF(E24-TODAY()<=15,"🟡 ATENÇÃO","🟢 OK"))))
... H34: =IF(F34="Pago","✓ OK",IF(E34="","",IF(E34<TODAY(),"🔴 VENCIDO",IF(E34-TODAY()<=15,"🟡 ATENÇÃO","🟢 OK"))))

Sheet Fluxo_de_Caixa
A1: FLUXO DE CAIXA — Visão 12 meses
A2: Entradas, saídas e saldo mensal
A4: Categoria | B4: Jan | C4: Fev | D4: Mar | E4: Abr | F4: Mai | G4: Jun | H4: Jul | I4: Ago | J4: Set | K4: Out | L4: Nov | M4: Dez | N4: Total
A5: ENTRADAS
A6: Vendas Cliente Final | B6: 0 | C6: 0 | D6: 0 | E6: 0 | F6: 0 | G6: 0 | H6: 0 | I6: 0 | J6: 0 | K6: 0 | L6: 0 | M6: 0 | N6: =SUM(B6:M6) -> 0
A7: Vendas Arquitetos | B7: 0 | C7: 0 | D7: 0 | E7: 0 | F7: 0 | G7: 0 | H7: 0 | I7: 0 | J7: 0 | K7: 0 | L7: 0 | M7: 0 | N7: =SUM(B7:M7) -> 0
A8: Vendas Reformistas | B8: 0 | C8: 0 | D8: 0 | E8: 0 | F8: 0 | G8: 0 | H8: 0 | I8: 0 | J8: 0 | K8: 0 | L8: 0 | M8: 0 | N8: =SUM(B8:M8) -> 0
A9: Vendas Construtoras | B9: 0 | C9: 0 | D9: 0 | E9: 0 | F9: 0 | G9: 0 | H9: 0 | I9: 0 | J9: 0 | K9: 0 | L9: 0 | M9: 0 | N9: =SUM(B9:M9) -> 0
A10: Outras Entradas | B10: 0 | C10: 0 | D10: 0 | E10: 0 | F10: 0 | G10: 0 | H10: 0 | I10: 0 | J10: 0 | K10: 0 | L10: 0 | M10: 0 | N10: =SUM(B10:M10) -> 0
A11: TOTAL ENTRADAS | B11: =SUM(B5:B10) -> 0 | C11: =SUM(C5:C10) -> 0 | D11: =SUM(D5:D10) -> 0 | E11: =SUM(E5:E10) -> 0 | F11: =SUM(F5:F10) -> 0 | G11: =SUM(G5:G10) -> 0 | H11: =SUM(H5:H10) -> 0 | I11: =SUM(I5:I10) -> 0 | ... M11: =SUM(M5:M10) -> 0 | N11: =SUM(B11:M11) -> 0
A13: SAÍDAS
A14: Materiais | B14: 0 | C14: 0 | D14: 0 | E14: 0 | F14: 0 | G14: 0 | H14: 0 | I14: 0 | J14: 0 | K14: 0 | L14: 0 | M14: 0 | N14: =SUM(B14:M14) -> 0
A15: Lacas/Vernizes | B15: 0 | C15: 0 | D15: 0 | E15: 0 | F15: 0 | G15: 0 | H15: 0 | I15: 0 | J15: 0 | K15: 0 | L15: 0 | M15: 0 | N15: =SUM(B15:M15) -> 0
A16: Ferragens | B16: 0 | C16: 0 | D16: 0 | E16: 0 | F16: 0 | G16: 0 | H16: 0 | I16: 0 | J16: 0 | K16: 0 | L16: 0 | M16: 0 | N16: =SUM(B16:M16) -> 0
A17: Folha Pagamento | B17: 0 | C17: 0 | D17: 0 | E17: 0 | F17: 0 | G17: 0 | H17: 0 | I17: 0 | J17: 0 | K17: 0 | L17: 0 | M17: 0 | N17: =SUM(B17:M17) -> 0
A18: Aluguel | B18: 0 | C18: 0 | D18: 0 | E18: 0 | F18: 0 | G18: 0 | H18: 0 | I18: 0 | J18: 0 | K18: 0 | L18: 0 | M18: 0 | N18: =SUM(B18:M18) -> 0
A19: Luz/Água | B19: 0 | C19: 0 | D19: 0 | E19: 0 | F19: 0 | G19: 0 | H19: 0 | I19: 0 | J19: 0 | K19: 0 | L19: 0 | M19: 0 | N19: =SUM(B19:M19) -> 0
A20: Combustível | B20: 0 | C20: 0 | D20: 0 | E20: 0 | F20: 0 | G20: 0 | H20: 0 | I20: 0 | J20: 0 | K20: 0 | L20: 0 | M20: 0 | N20: =SUM(B20:M20) -> 0
A21: Gestoria/Seguros | B21: 0 | C21: 0 | D21: 0 | E21: 0 | F21: 0 | G21: 0 | H21: 0 | I21: 0 | J21: 0 | K21: 0 | L21: 0 | M21: 0 | N21: =SUM(B21:M21) -> 0
A22: Impostos | B22: 0 | C22: 0 | D22: 0 | E22: 0 | F22: 0 | G22: 0 | H22: 0 | I22: 0 | J22: 0 | K22: 0 | L22: 0 | M22: 0 | N22: =SUM(B22:M22) -> 0
A23: Outras Saídas | B23: 0 | C23: 0 | D23: 0 | E23: 0 | F23: 0 | G23: 0 | H23: 0 | I23: 0 | J23: 0 | K23: 0 | L23: 0 | M23: 0 | N23: =SUM(B23:M23) -> 0
A24: TOTAL SAÍDAS | B24: =SUM(B13:B22) -> 0 | C24: =SUM(C13:C22) -> 0 | D24: =SUM(D13:D22) -> 0 | E24: =SUM(E13:E22) -> 0 | F24: =SUM(F13:F22) -> 0 | G24: =SUM(G13:G22) -> 0 | H24: =SUM(H13:H22) -> 0 | I24: =SUM(I13:I22) -> 0 | ... M24: =SUM(M13:M22) -> 0 | N24: =SUM(B24:M24) -> 0
A26: SALDO MENSAL | B26: =B11-B23 -> 0 | C26: =C11-C23 -> 0 | D26: =D11-D23 -> 0 | E26: =E11-E23 -> 0 | F26: =F11-F23 -> 0 | G26: =G11-G23 -> 0 | H26: =H11-H23 -> 0 | I26: =I11-I23 -> 0 | ... M26: =M11-M23 -> 0 | N26: =SUM(B26:M26) -> 0
A27: SALDO ACUMULADO | B27: =B25 -> 0 | C27: =B26+C25 -> 0 | D27: =C26+D25 -> 0 | E27: =D26+E25 -> 0 | F27: =E26+F25 -> 0 | G27: =F26+G25 -> 0 | H27: =G26+H25 -> 0 | I27: =H26+I25 -> 0 | J27: =I26+J25 -> 0 | ... M27: =L26+M25 -> 0 | N27: =SUM(B27:M27) -> 0
